evlatools/__init__.py
evlatools/case/__init__.py
evlatools/case/case.py
evlatools/case/provider.py
evlatools/client/__init__.py
evlatools/client/httpclient.py
evlatools/client/media.py
evlatools/comm/__init__.py
evlatools/comm/_cache.py
evlatools/comm/_date.py
evlatools/comm/_mock.py
evlatools/comm/cryptolib.py
evlatools/comm/dbconn.py
evlatools/comm/jsonpath.py
evlatools/comm/loadfile.py
evlatools/comm/template.py
evlatools/comm/validator.py
evlatools/launch.py
evlatools-0.1.21.dist-info/METADATA
evlatools-0.1.21.dist-info/WHEEL
evlatools-0.1.21.dist-info/RECORD
